troopy/__init__.py
troopy/errors.py
troopy/message_bus.py
troopy/message_router.py
troopy-0.1.0.dist-info/LICENSE
troopy-0.1.0.dist-info/WHEEL
troopy-0.1.0.dist-info/METADATA
troopy-0.1.0.dist-info/RECORD
