Metadata-Version: 2.1
Name: troopy
Version: 0.1.0
Summary: Command Bus/Message Bus implementation for python
Home-page: https://github.com/kodemore/troopy
License: MIT
Keywords: troopy,command,command bus,ddd,message,message bus,command router
Author: Dawid Kraczkowski
Author-email: dawid.kraczkowski@gmail.com
Requires-Python: >=3.6,<4.0
Classifier: Development Status :: 5 - Production/Stable
Classifier: Intended Audience :: Developers
Classifier: License :: OSI Approved :: MIT License
Classifier: Natural Language :: English
Classifier: Programming Language :: Python
Classifier: Programming Language :: Python :: 3
Classifier: Programming Language :: Python :: 3.6
Classifier: Programming Language :: Python :: 3.7
Classifier: Programming Language :: Python :: 3.8
Classifier: Topic :: Software Development :: Libraries
Classifier: Topic :: Software Development :: Libraries :: Python Modules
Requires-Dist: typing_extensions (>=3.7.4,<4.0.0)
Project-URL: Documentation, https://github.com/kodemore/troopy
Project-URL: Repository, https://github.com/kodemore/troopy
